m3_legacy/__init__.py
m3_legacy/config.py
m3_legacy/datagrouping.py
m3_legacy/datastructures.py
m3_legacy/db.py
m3_legacy/loader.py
m3_legacy/logger.py
m3_legacy/middleware.py
m3_legacy/plugins.py
m3_legacy/validation.py
m3_legacy-2.2.0.dist-info/METADATA
m3_legacy-2.2.0.dist-info/WHEEL
m3_legacy-2.2.0.dist-info/top_level.txt
m3_legacy-2.2.0.dist-info/RECORD
