Metadata-Version: 2.4
Name: m3-legacy
Version: 2.2.0
Home-page: https://bitbucket.org/barsgroup/m3-legacy
Author: BARS Group
Author-email: bars@bars-open.ru
License: MIT
Classifier: Intended Audience :: Developers
Classifier: Environment :: Web Environment
Classifier: Natural Language :: Russian
Classifier: Natural Language :: English
Classifier: Operating System :: OS Independent
Classifier: Programming Language :: Python
Classifier: License :: OSI Approved :: MIT License
Classifier: Development Status :: 5 - Production/Stable
Requires-Dist: six>=1.11
Requires-Dist: django>=1.4
Requires-Dist: m3-django-compatibility>=1.12.0
Requires-Dist: m3-core
Dynamic: author
Dynamic: author-email
Dynamic: classifier
Dynamic: description
Dynamic: home-page
Dynamic: license
Dynamic: requires-dist
